{
  "type": "minecraft:entity",
  "pools": [
    {
      "rolls": 1,
      "entries": [
        {
          "type": "minecraft:item",
          "name": "cataclysm:lacrima",
          "functions": [
            {
              "function": "minecraft:set_count",
              "count": {
                "type": "minecraft:uniform",
                "min": 8,
                "max": 16
              }
            }
          ]
        }
      ]
    },
    {
      "rolls": 1,
      "entries": [
        {
          "type": "minecraft:item",
          "name": "cataclysm:essence_of_the_storm",
          "functions": [
            {
              "function": "minecraft:set_count",
              "count": {
                "type": "minecraft:uniform",
                "min": 3,
                "max": 4
              }
            }
          ]
        }
      ]
    },
    {
      "name": "disc",
      "conditions": [
        {
          "condition": "random_chance_with_looting",
          "chance": 0.1,
          "looting_multiplier": 0.1
        }
      ],
      "rolls": 1,
      "entries": [
        {
          "type": "minecraft:item",
          "name": "cataclysm:music_disc_scylla",
          "weight": 1
        }
      ]
    }
  ]
}